mypackage/__init__.py
removeb-0.1.0.dist-info/METADATA
removeb-0.1.0.dist-info/WHEEL
removeb-0.1.0.dist-info/top_level.txt
removeb-0.1.0.dist-info/RECORD
